LICENCE
MANIFEST.in
README.rst
setup.py
docs/blank.txt
geoalgo/__init__.py
geoalgo/admin.py
geoalgo/algo_tree.py
geoalgo/apps.py
geoalgo/models.py
geoalgo/tests.py
geoalgo/views.py
geoalgo.egg-info/PKG-INFO
geoalgo.egg-info/SOURCES.txt
geoalgo.egg-info/dependency_links.txt
geoalgo.egg-info/top_level.txt
geoalgo/migrations/__init__.py